paircorr/__init__.py
paircorr/log.py
paircorr/pair_plot.py
paircorr/reg_plot.py
paircorr/scatter_with_reg.py
paircorr-0.0.1.dist-info/METADATA
paircorr-0.0.1.dist-info/WHEEL
paircorr-0.0.1.dist-info/top_level.txt
paircorr-0.0.1.dist-info/RECORD
